pytelemetrycli/__init__.py
pytelemetrycli/cli.py
pytelemetrycli/example.py
pytelemetrycli/initialization.py
pytelemetrycli/runner.py
pytelemetrycli/tools.py
pytelemetrycli/topics.py
pytelemetrycli/ui/__init__.py
pytelemetrycli/ui/superplot.py
pytelemetrycli-1.1.0.dist-info/DESCRIPTION.rst
pytelemetrycli-1.1.0.dist-info/METADATA
pytelemetrycli-1.1.0.dist-info/RECORD
pytelemetrycli-1.1.0.dist-info/WHEEL
pytelemetrycli-1.1.0.dist-info/entry_points.txt
pytelemetrycli-1.1.0.dist-info/metadata.json
pytelemetrycli-1.1.0.dist-info/top_level.txt
