Metadata-Version: 2.0
Name: pytelemetrycli
Version: 1.1.0
Summary: command-line interface for data visualization and communication with embedded devices
Home-page: https://github.com/Overdrivr/pytelemetrycli
Author: Rémi Bèges
Author-email: remi.beges@gmail.com
License: MIT
Keywords: cli plot debug lightweight communication protocol embedded telemetry remote program control
Platform: UNKNOWN
Classifier: Development Status :: 4 - Beta
Classifier: Intended Audience :: Developers
Classifier: Intended Audience :: End Users/Desktop
Classifier: Intended Audience :: Telecommunications Industry
Classifier: Topic :: Communications
Classifier: Topic :: Scientific/Engineering :: Human Machine Interfaces
Classifier: Topic :: Software Development :: Embedded Systems
Classifier: Topic :: Software Development :: Libraries :: Python Modules
Classifier: License :: OSI Approved :: MIT License
Classifier: Programming Language :: Python :: 3.3
Classifier: Programming Language :: Python :: 3.4
Classifier: Programming Language :: Python :: 3.5
Requires-Dist: docopt
Requires-Dist: numpy
Requires-Dist: pyqtgraph
Requires-Dist: pyserial (>3.0.0)
Requires-Dist: pytelemetry (>=1.1.6)
Requires-Dist: sortedcontainers
Provides-Extra: dev
Requires-Dist: check-manifest; extra == 'dev'
Provides-Extra: test
Requires-Dist: pytest; extra == 'test'
Requires-Dist: pytest-cov; extra == 'test'
